discordpydebug/__init__.py
discordpydebug/__main__.py
discordpydebug-0.0.4.dist-info/LICENSE
discordpydebug-0.0.4.dist-info/METADATA
discordpydebug-0.0.4.dist-info/WHEEL
discordpydebug-0.0.4.dist-info/top_level.txt
discordpydebug-0.0.4.dist-info/RECORD
