Metadata-Version: 2.1
Name: discordpydebug
Version: 0.0.4
Summary: Discord py error logger
Home-page: https://github.com/
Author: JadenV
Author-email: JadenV@discordaddons.com
License: UNKNOWN
Project-URL: Bug Tracker, https://github.com/
Platform: UNKNOWN
Classifier: Programming Language :: Python :: 3
Classifier: License :: OSI Approved :: MIT License
Classifier: Operating System :: OS Independent
Requires-Python: >=3.6
License-File: LICENSE
